__init__.py
alma_api.py
almalibri_client-2.1.0.dist-info/METADATA
almalibri_client-2.1.0.dist-info/WHEEL
almalibri_client-2.1.0.dist-info/entry_points.txt
almalibri_client-2.1.0.dist-info/top_level.txt
almalibri_client-2.1.0.dist-info/RECORD
