Metadata-Version: 2.2
Name: almalibri_client
Version: 2.1.0
Summary: A client for AlmaLibri API
Author-email: Claudio Tubertini <info@almalibri.it>
Project-URL: Homepage, https://github.com/claudiotubertini/api_almalibri
Project-URL: Issues, https://github.com/claudiotubertini/api_almalibri/issues
Classifier: Programming Language :: Python :: 3
Classifier: License :: OSI Approved :: GNU General Public License v2 or later (GPLv2+)
Classifier: Operating System :: OS Independent
Classifier: Intended Audience :: Developers
Classifier: Development Status :: 5 - Production/Stable
Requires-Python: >=3.9
Requires-Dist: requests>=2.31.0
Requires-Dist: click
Requires-Dist: pandas
